nai_t5/__init__.py
nai_t5/checkpoint_info.py
nai_t5/flex_utils.py
nai_t5/fuse_norm_scales.py
nai_t5/replace_linear.py
nai_t5/sampling.py
nai_t5/sp_add_mask_vocab.py
nai_t5/t5.py
nai_t5/t5_common.py
nai_t5/t5_decoder.py
nai_t5/t5_encoder.py
nai_t5/t5_hf.py
nai_t5/weight_load.py
nai_t5/scripts/__init__.py
nai_t5/scripts/benchmark_attn.py
nai_t5/scripts/benchmark_encoder.py
nai_t5/scripts/t5_bucket_test.py
nai_t5/scripts/t5_encdec_parity.py
nai_t5/scripts/t5_encdec_precision_parity.py
nai_t5/scripts/t5_encoder_flex_parity.py
nai_t5/scripts/t5_encoder_hf_precision_parity.py
nai_t5/scripts/t5_encoder_parity.py
nai_t5/scripts/t5_encoder_parity_fsdp.py
nai_t5/scripts/t5_encoder_precision_parity.py
nai_t5/scripts/t5_flex_buckets.py
nai_t5/scripts/t5_sampling_hf_generate.py
nai_t5/scripts/t5_sampling_parity_cache.py
nai_t5/scripts/t5_sampling_parity_nocache.py
nai_t5/scripts/t5_serialize.py
nai_t5/scripts/t5_serialize_dtensor.py
nai_t5/scripts/tokenizer_hf_to_sentencepiece.py
nai_t5/scripts/umt5_encdec_parity.py
nai_t5/scripts/umt5_encoder_parity.py
nai_t5-1.0.10.dist-info/METADATA
nai_t5-1.0.10.dist-info/WHEEL
nai_t5-1.0.10.dist-info/entry_points.txt
nai_t5-1.0.10.dist-info/licenses/LICENSE
nai_t5-1.0.10.dist-info/RECORD
