Metadata-Version: 2.4
Name: nai-t5
Version: 1.0.10
Summary: NovelAI T5
Project-URL: Homepage, https://github.com/NovelAI/t5
Project-URL: Issue Tracker, https://github.com/NovelAI/t5/issues
Author: NovelAI/Anlatan Inc.
License: Apache-2.0
License-File: LICENSE
Keywords: novelai,t5
Requires-Python: >=3.10
Requires-Dist: einops
Requires-Dist: pydantic
Requires-Dist: torch
Provides-Extra: bench
Requires-Dist: tabulate; extra == 'bench'
Requires-Dist: triton; extra == 'bench'
Provides-Extra: hf
Requires-Dist: tokenizers; extra == 'hf'
Requires-Dist: transformers; extra == 'hf'
Provides-Extra: sp
Requires-Dist: sentencepiece; extra == 'sp'
Provides-Extra: tensorizer
Requires-Dist: tensorizer; extra == 'tensorizer'
